src/.env
src/Pipfile
src/Pipfile.lock
src/README.md
src/config.json
src/langgraph.json
src/requirement.txt
src/results.md
src/test_demo_server.py
src/test_gedaia_agent.py
src/test_gedaia_chat.py
src/.gradio/certificate.pem
src/.langgraph_api/.langgraph_checkpoint.1.pckl
src/.langgraph_api/.langgraph_checkpoint.2.pckl
src/.langgraph_api/.langgraph_checkpoint.3.pckl
src/.langgraph_api/.langgraph_ops.pckl
src/.langgraph_api/.langgraph_retry_counter.pckl
src/.langgraph_api/store.pckl
src/.langgraph_api/store.vectors.pckl
src/.vscode/launch.json
src/aig/__init__.py
src/aig/agents/gedaia/__init__.py
src/aig/agents/gedaia/gedaia_agent.py
src/aig/agents/gedaia/gedaia_chat.py
src/aig/agents/server/Pipfile
src/aig/agents/server/math_server.py
src/aig/agents/server/package-lock.json
src/aig/domain/mcp_client.py
src/db/gedaiaChat.db
gedaia_agent-0.0.4.dist-info/METADATA
gedaia_agent-0.0.4.dist-info/WHEEL
gedaia_agent-0.0.4.dist-info/licenses/LICENSE
gedaia_agent-0.0.4.dist-info/RECORD
