Metadata-Version: 2.4
Name: gedaia_agent
Version: 0.0.4
Dynamic: Requires-Dist
Summary: Agent GeDAIA pour le Notariat
Project-URL: Homepage, https://dev.azure.com/LexFluent2020/RevolutionAI
Project-URL: Issues, https://dev.azure.com/LexFluent2020/RevolutionAI/_queries/query/180a1ed2-3494-42cc-8d8a-2e60217c2171/
Author-email: Jacques MASSA <jacques.massa@lexfluent.com>
License-File: LICENSE
Classifier: License :: OSI Approved :: MIT License
Classifier: Operating System :: OS Independent
Classifier: Programming Language :: Python :: 3
Requires-Python: >=3.12
